project_async/__init__.py
project_async/client.py
project_async/errors.py
project_async/model.py
project_async-0.0.1rc105.post1.dist-info/LICENSE
project_async-0.0.1rc105.post1.dist-info/WHEEL
project_async-0.0.1rc105.post1.dist-info/METADATA
project_async-0.0.1rc105.post1.dist-info/RECORD
