Metadata-Version: 2.1
Name: project-async
Version: 0.0.1rc105.post1
Summary: Sample Python Project for creating a new Python Async Client for a new API
Author-email: Alberto Montes <al.montes.gomez@gmail.com>
Requires-Python: >=3.11
Classifier: Development Status :: 3 - Alpha
Classifier: Intended Audience :: Developers
Classifier: License :: OSI Approved :: MIT License
Classifier: Programming Language :: Python :: 3 :: Only
Classifier: Programming Language :: Python :: 3.8
Classifier: Programming Language :: Python :: 3.9
Classifier: Programming Language :: Python :: 3.10
Classifier: Programming Language :: Python :: 3.11
Classifier: Programming Language :: Python :: 3.12
Requires-Dist: aiohttp==3.10.9
Requires-Dist: dataclasses-json==0.6.7
Requires-Dist: bandit[toml]==1.7.10 ; extra == "dev"
Requires-Dist: black==24.8.0 ; extra == "dev"
Requires-Dist: check-manifest==0.49 ; extra == "dev"
Requires-Dist: flake8-bugbear==24.8.19 ; extra == "dev"
Requires-Dist: flake8-docstrings ; extra == "dev"
Requires-Dist: flake8-formatter_junit_xml ; extra == "dev"
Requires-Dist: flake8 ; extra == "dev"
Requires-Dist: flake8-pyproject ; extra == "dev"
Requires-Dist: isort==5.13.2 ; extra == "dev"
Requires-Dist: pre-commit==4.0.0 ; extra == "dev"
Requires-Dist: pylint==3.3.1 ; extra == "dev"
Requires-Dist: pytest-cov==5.0.0 ; extra == "dev"
Requires-Dist: pytest-mock<3.14.1 ; extra == "dev"
Requires-Dist: pytest-runner ; extra == "dev"
Requires-Dist: pytest==8.3.3 ; extra == "dev"
Requires-Dist: pytest-github-actions-annotate-failures ; extra == "dev"
Requires-Dist: pytype ; extra == "dev"
Requires-Dist: shellcheck-py==0.10.0.1 ; extra == "dev"
Project-URL: Documentation, https://github.com/albertomontesg/python-async-api-client/blob/main/README.md
Project-URL: Source, https://github.com/albertomontesg/python-async-api-client
Project-URL: Tracker, https://github.com/albertomontesg/python-async-api-client/issues
Provides-Extra: dev
